castella/__init__.py
castella/async_net_image.py
castella/box.py
castella/build_owner.py
castella/button.py
castella/canvaskit_painter.py
castella/checkbox.py
castella/color.py
castella/column.py
castella/core.py
castella/datetime_input.py
castella/diff_view.py
castella/file_tree.py
castella/font.py
castella/font_fallback.py
castella/glfw_frame.py
castella/image.py
castella/input.py
castella/ios_frame.py
castella/modal.py
castella/multiline_input.py
castella/multiline_text.py
castella/net_image.py
castella/numpy_image.py
castella/progressbar.py
castella/pt_frame.py
castella/pt_painter.py
castella/radio_buttons.py
castella/row.py
castella/rust_skia_painter.py
castella/sdl3_frame.py
castella/sdl_frame.py
castella/slider.py
castella/spacer.py
castella/switch.py
castella/table.py
castella/tabs.py
castella/text.py
castella/tree.py
castella/web_frame.py
castella/a2a/__init__.py
castella/a2a/client.py
castella/a2a/types.py
castella/a2ui/__init__.py
castella/a2ui/_factories.py
castella/a2ui/catalog.py
castella/a2ui/client.py
castella/a2ui/compat.py
castella/a2ui/renderer.py
castella/a2ui/stream.py
castella/a2ui/transports.py
castella/a2ui/types.py
castella/agent/__init__.py
castella/agent/agent_chat.py
castella/agent/card_view.py
castella/agent/chat.py
castella/agent/hub.py
castella/agent/multi.py
castella/agent/tool_view.py
castella/animation/__init__.py
castella/animation/animated_state.py
castella/animation/animation.py
castella/animation/easing.py
castella/animation/interpolators.py
castella/animation/scheduler.py
castella/animation/tween.py
castella/audio/__init__.py
castella/audio/manager.py
castella/audio/protocols.py
castella/audio/state.py
castella/audio/backends/__init__.py
castella/audio/backends/noop.py
castella/audio/backends/sdl_mixer.py
castella/audio/widgets/__init__.py
castella/audio/widgets/audio_player.py
castella/calendar/__init__.py
castella/calendar/day_cell.py
castella/calendar/grid.py
castella/calendar/header.py
castella/calendar/locale.py
castella-0.15.4.dist-info/METADATA
castella-0.15.4.dist-info/WHEEL
castella-0.15.4.dist-info/licenses/LICENSE
castella-0.15.4.dist-info/RECORD
