Metadata-Version: 2.3
Name: castella
Version: 0.15.4
Summary: Castella is a pure Python cross-platform UI framework
Project-URL: homepage, https://github.com/i2y/castella
Project-URL: repository, https://github.com/i2y/castella
Project-URL: documentation, https://i2y.github.io/castella
Author-email: Yasushi Itoh <i2y@icloud.com>
License: MIT
Classifier: Development Status :: 4 - Beta
Classifier: License :: OSI Approved :: MIT License
Classifier: Programming Language :: Python :: 3
Classifier: Programming Language :: Python :: 3.11
Classifier: Programming Language :: Python :: 3.12
Classifier: Programming Language :: Python :: 3.13
Classifier: Programming Language :: Python :: 3.14
Classifier: Topic :: Software Development :: Libraries :: Python Modules
Requires-Python: >=3.11
Provides-Extra: agent
Requires-Dist: python-a2a>=0.5.0; extra == 'agent'
Provides-Extra: audio
Requires-Dist: pydantic>=2.7.4; extra == 'audio'
Requires-Dist: pysdl2-dll>=2.30.2; extra == 'audio'
Requires-Dist: pysdl2>=0.9.16; extra == 'audio'
Provides-Extra: edda-workflow-manager
Requires-Dist: edda-framework[llamaindex]>=0.15.0; extra == 'edda-workflow-manager'
Requires-Dist: llama-index-core>=0.12.0; extra == 'edda-workflow-manager'
Provides-Extra: glfw
Requires-Dist: castella-skia>=0.1.4; extra == 'glfw'
Requires-Dist: darkdetect>=0.8; extra == 'glfw'
Requires-Dist: glfw>=2.7.0; extra == 'glfw'
Requires-Dist: markdown-it-py>=3.0.0; extra == 'glfw'
Requires-Dist: matplotlib>=3.9.0; extra == 'glfw'
Requires-Dist: mdit-py-plugins>=0.4.0; extra == 'glfw'
Requires-Dist: pydantic>=2.7.4; extra == 'glfw'
Requires-Dist: pygments>=2.17.0; extra == 'glfw'
Requires-Dist: pyobjc-framework-cocoa>=10.0; (sys_platform == 'darwin') and extra == 'glfw'
Requires-Dist: pyopengl>=3.1.7; extra == 'glfw'
Provides-Extra: ios
Requires-Dist: pydantic>=2.7.4; extra == 'ios'
Requires-Dist: rubicon-objc>=0.4.9; extra == 'ios'
Provides-Extra: langgraph-studio
Requires-Dist: langchain-core>=0.3.0; extra == 'langgraph-studio'
Requires-Dist: langgraph>=0.2.0; extra == 'langgraph-studio'
Provides-Extra: llamaindex-studio
Requires-Dist: llama-index-core>=0.12.0; extra == 'llamaindex-studio'
Provides-Extra: mcp
Requires-Dist: mcp>=1.0.0; extra == 'mcp'
Provides-Extra: pydantic-graph-studio
Requires-Dist: pydantic-graph>=0.1.0; extra == 'pydantic-graph-studio'
Provides-Extra: sdl
Requires-Dist: castella-skia>=0.1.4; extra == 'sdl'
Requires-Dist: darkdetect>=0.8; extra == 'sdl'
Requires-Dist: markdown-it-py>=3.0.0; extra == 'sdl'
Requires-Dist: matplotlib>=3.9.0; extra == 'sdl'
Requires-Dist: mdit-py-plugins>=0.4.0; extra == 'sdl'
Requires-Dist: pydantic>=2.7.4; extra == 'sdl'
Requires-Dist: pygments>=2.17.0; extra == 'sdl'
Requires-Dist: pyopengl>=3.1.7; extra == 'sdl'
Requires-Dist: pysdl2-dll>=2.30.2; extra == 'sdl'
Requires-Dist: pysdl2>=0.9.16; extra == 'sdl'
Provides-Extra: sdl3
Requires-Dist: castella-skia>=0.1.4; extra == 'sdl3'
Requires-Dist: darkdetect>=0.8; extra == 'sdl3'
Requires-Dist: markdown-it-py>=3.0.0; extra == 'sdl3'
Requires-Dist: matplotlib>=3.9.0; extra == 'sdl3'
Requires-Dist: mdit-py-plugins>=0.4.0; extra == 'sdl3'
Requires-Dist: pydantic>=2.7.4; extra == 'sdl3'
Requires-Dist: pygments>=2.17.0; extra == 'sdl3'
Requires-Dist: pyopengl>=3.1.7; extra == 'sdl3'
Requires-Dist: pysdl3>=0.9.10b0; extra == 'sdl3'
Provides-Extra: tui
Requires-Dist: darkdetect>=0.8; extra == 'tui'
Requires-Dist: markdown-it-py>=3.0.0; extra == 'tui'
Requires-Dist: mdit-py-plugins>=0.4.0; extra == 'tui'
Requires-Dist: prompt-toolkit>=3.0.48; extra == 'tui'
Requires-Dist: pydantic>=2.7.4; extra == 'tui'
Requires-Dist: pygments>=2.17.0; extra == 'tui'
Requires-Dist: pyperclip>=1.9.0; extra == 'tui'
Requires-Dist: windows-curses>=2.3.3; (sys_platform == 'win32') and extra == 'tui'
